{
  "cameras": [
    {
      "name": "C치mara Dahua Hero-K51H",
      "ip": "192.168.1.172",
      "username": "admin",
      "password": "3gfwb3ToWfeWNqm22223DGbzcH-4si",
      "type": "rtsp",
      "brand": "dahua",
      "onvif_port": 80,
      "rtsp_port": 554,
      "http_port": 80
    },
    {
      "name": "C치mara TP-Link Tapo C320WS",
      "ip": "192.168.1.77",
      "username": "admin-tato",
      "password": "mUidGT87gMxg8ce!Wxso3Guu8t.3*Q",
      "type": "onvif",
      "brand": "tplink",
      "onvif_port": 2020,
      "rtsp_port": 554,
      "http_port": 80
    },
    {
      "name": "C치mara Steren CCTV-235",
      "ip": "192.168.1.178",
      "username": "admin",
      "password": "-wFNC2tR_dTVqxyGsTE.p2Zihy.ZgH",
      "type": "onvif",
      "brand": "steren",
      "onvif_port": 8000,
      "rtsp_port": 554,
      "http_port": 80
    },
    {
      "name": "C치mara Generic China",
      "ip": "192.168.1.180",
      "username": "EightMPWiFiSCmr",
      "password": "2gZNaWLtV6qi49KeANQ3wh7dDfNnoF",
      "type": "rtsp",
      "brand": "generic",
      "onvif_port": 80,
      "rtsp_port": 554,
      "http_port": 80
    }
  ],
  "layout": 2,
  "version": "2.0",
  "timestamp": "2025-06-13 00:49:34"
}